cuenca/__init__.py
cuenca/exc.py
cuenca/jwt.py
cuenca/py.typed
cuenca/version.py
cuenca/http/__init__.py
cuenca/http/client.py
cuenca/resources/__init__.py
cuenca/resources/accounts.py
cuenca/resources/api_keys.py
cuenca/resources/arpc.py
cuenca/resources/balance_entries.py
cuenca/resources/base.py
cuenca/resources/bill_payments.py
cuenca/resources/card_activations.py
cuenca/resources/card_transactions.py
cuenca/resources/card_validations.py
cuenca/resources/cards.py
cuenca/resources/cash_references.py
cuenca/resources/clabes.py
cuenca/resources/commissions.py
cuenca/resources/curp_validations.py
cuenca/resources/deposits.py
cuenca/resources/endpoints.py
cuenca/resources/exist_phones.py
cuenca/resources/file_batches.py
cuenca/resources/files.py
cuenca/resources/identities.py
cuenca/resources/identity_events.py
cuenca/resources/jwt_tokens.py
cuenca/resources/kyc_validations.py
cuenca/resources/limited_wallets.py
cuenca/resources/login_tokens.py
cuenca/resources/otps.py
cuenca/resources/phone_verification_associations.py
cuenca/resources/platforms.py
cuenca/resources/postal_codes.py
cuenca/resources/questionnaires.py
cuenca/resources/resources.py
cuenca/resources/savings.py
cuenca/resources/service_providers.py
cuenca/resources/sessions.py
cuenca/resources/statements.py
cuenca/resources/terms_of_service.py
cuenca/resources/transfers.py
cuenca/resources/user_credentials.py
cuenca/resources/user_events.py
cuenca/resources/user_lists_validation.py
cuenca/resources/user_logins.py
cuenca/resources/users.py
cuenca/resources/users_tos_agreements.py
cuenca/resources/verifications.py
cuenca/resources/wallet_transactions.py
cuenca/resources/webhooks.py
cuenca/resources/whatsapp_transfers.py
cuenca-2.1.16.dist-info/licenses/LICENSE
tests/__init__.py
tests/conftest.py
tests/test_cuenca.py
tests/test_jwt.py
tests/http/__init__.py
tests/http/conftest.py
tests/http/test_client.py
tests/resources/__init__.py
tests/resources/test_accounts.py
tests/resources/test_api_keys.py
tests/resources/test_arpc.py
cuenca-2.1.16.dist-info/METADATA
cuenca-2.1.16.dist-info/WHEEL
cuenca-2.1.16.dist-info/top_level.txt
cuenca-2.1.16.dist-info/RECORD
