Metadata-Version: 2.4
Name: cuenca
Version: 2.1.16
Summary: Cuenca API Client
Home-page: https://github.com/cuenca-mx/cuenca-python
Author: Cuenca
Author-email: dev@cuenca.com
Classifier: Programming Language :: Python :: 3.9
Classifier: Programming Language :: Python :: 3.10
Classifier: Programming Language :: Python :: 3.11
Classifier: Programming Language :: Python :: 3.12
Classifier: Programming Language :: Python :: 3.13
Classifier: License :: OSI Approved :: MIT License
Classifier: Operating System :: OS Independent
Requires-Python: >=3.9
License-File: LICENSE
Requires-Dist: requests>=2.32.0
Requires-Dist: cuenca-validations>=2.1.5
Requires-Dist: pydantic-extra-types>=2.10.0
Dynamic: author
Dynamic: author-email
Dynamic: classifier
Dynamic: description
Dynamic: description-content-type
Dynamic: home-page
Dynamic: license-file
Dynamic: requires-dist
Dynamic: requires-python
Dynamic: summary
